odoo/addons/purchase_uninvoiced_amount_force_invoiced_line/README.rst
odoo/addons/purchase_uninvoiced_amount_force_invoiced_line/__init__.py
odoo/addons/purchase_uninvoiced_amount_force_invoiced_line/__manifest__.py
odoo/addons/purchase_uninvoiced_amount_force_invoiced_line/i18n/it.po
odoo/addons/purchase_uninvoiced_amount_force_invoiced_line/i18n/purchase_uninvoiced_amount_force_invoiced_line.pot
odoo/addons/purchase_uninvoiced_amount_force_invoiced_line/models/__init__.py
odoo/addons/purchase_uninvoiced_amount_force_invoiced_line/models/purchase_order_line.py
odoo/addons/purchase_uninvoiced_amount_force_invoiced_line/readme/CONTRIBUTORS.md
odoo/addons/purchase_uninvoiced_amount_force_invoiced_line/readme/DESCRIPTION.md
odoo/addons/purchase_uninvoiced_amount_force_invoiced_line/static/description/icon.png
odoo/addons/purchase_uninvoiced_amount_force_invoiced_line/static/description/index.html
odoo/addons/purchase_uninvoiced_amount_force_invoiced_line/tests/__init__.py
odoo/addons/purchase_uninvoiced_amount_force_invoiced_line/tests/test_purchase_uninvoiced_amount_force_invoiced_line.py
odoo_addon_purchase_uninvoiced_amount_force_invoiced_line-18.0.1.0.0.4.dist-info/METADATA
odoo_addon_purchase_uninvoiced_amount_force_invoiced_line-18.0.1.0.0.4.dist-info/WHEEL
odoo_addon_purchase_uninvoiced_amount_force_invoiced_line-18.0.1.0.0.4.dist-info/top_level.txt
odoo_addon_purchase_uninvoiced_amount_force_invoiced_line-18.0.1.0.0.4.dist-info/RECORD
