Metadata-Version: 2.1
Name: odoo-addon-purchase_uninvoiced_amount_force_invoiced_line
Version: 18.0.1.0.0.4
Requires-Python: >=3.10
Requires-Dist: odoo-addon-purchase_invoice_status_line==18.0.*
Requires-Dist: odoo-addon-purchase_order_uninvoiced_amount_line==18.0.*
Requires-Dist: odoo==18.0.*
Summary: Glue module between uninvoiced amount line and force invoiced line
Home-page: https://github.com/OCA/purchase-workflow
License: AGPL-3
Author: ForgeFlow, Odoo Community Association (OCA)
Author-email: support@odoo-community.org
Classifier: Programming Language :: Python
Classifier: Framework :: Odoo
Classifier: Framework :: Odoo :: 18.0
Classifier: License :: OSI Approved :: GNU Affero General Public License v3
